{
  "narrows-top-down-zion-ut": 78,
  "mist-trail-vernal-fall-ca": 88,
  "paria-canyon-az": 78,
  "hanging-lake-co": 100,
  "nelson-ghost-town-nv": 78,
  "mount-moriah-nv": 60,
  "wheeler-peak-great-basin-nv": 60,
  "wire-pass-buckskin-az": 50,
  "rhyolite-ghost-town-nv": 88,
  "cathedral-gorge-nv": 50,
  "wave-rock-valley-of-fire-nv": 60,
  "maroon-bells-crater-lake-co": 60,
  "south-kaibab-gc-az": 78,
  "toroweap-overlook-az": 78,
  "mary-jane-falls-nv": 60,
  "havasu-falls-az": 60,
  "kanarra-creek-ut": 78,
  "marlette-lake-ca": 88,
  "bryce-rim-trail-ut": 90,
  "bright-angel-trail-gc-az": 78,
  "black-canyon-water-trail-nv": 60,
  "half-dome-yosemite-ca": 88,
  "river-mountains-loop-nv": 78,
  "snow-canyon-rim-ut": 78,
  "emerald-lake-rmnp-co": 78,
  "hoover-dam-trail-nv": 60,
  "angels-landing-zion-ut": 78,
  "west-fork-oak-creek-az": 78,
  "crystal-cove-el-moro-ca": 100,
  "pine-valley-mountain-ut": 90,
  "charleston-peak-nv": 70,
  "mount-whitney-ca": 60,
  "the-narrows-zion-ut": 78,
  "petroglyph-canyon-gold-butte-nv": 78,
  "peek-a-boo-loop-bryce-ut": 90,
  "kanab-creek-wilderness-az": 78,
  "hermit-trail-gc-az": 78,
  "garden-of-the-gods-co": 100,
  "ice-lake-basin-co": 60,
  "calico-hills-red-rock-nv": 90
}