{
  "trail_id": "3",
  "name": "Bryce Canyon Rim Trail",
  "slug": "bryce-rim-trail-ut",
  "state": "UT",
  "region": "Southwest",
  "lat": "37.6402",
  "lng": "-112.1679",
  "difficulty": "Easy",
  "length_mi": "11",
  "status": "Open",
  "score": 40,
  "score_label": "Conditions poor",
  "gear_flags": [
    "wind layer recommended",
    "insulation layer required"
  ],
  "current": {
    "temp_f": 38,
    "feels_like_f": 29,
    "wind_mph": 13,
    "gusts_mph": 28,
    "rain_pct": 16
  },
  "aqi": {
    "aqi": null,
    "category": "Unknown",
    "pollutant": ""
  },
  "forecast": [
    {
      "date": "2026-04-01",
      "high_f": 48,
      "low_f": 34,
      "rain_pct": 70,
      "uv": 7
    },
    {
      "date": "2026-04-02",
      "high_f": 50,
      "low_f": 29,
      "rain_pct": 12,
      "uv": 8
    },
    {
      "date": "2026-04-03",
      "high_f": 48,
      "low_f": 20,
      "rain_pct": 12,
      "uv": 7
    },
    {
      "date": "2026-04-04",
      "high_f": 53,
      "low_f": 28,
      "rain_pct": 0,
      "uv": 8
    },
    {
      "date": "2026-04-05",
      "high_f": 57,
      "low_f": 36,
      "rain_pct": 2,
      "uv": 7
    }
  ],
  "updated_at": "2026-04-01T06:22:37.704382+00:00"
}