{
  "trail_id": "39",
  "name": "Crystal Cove Beach to El Moro",
  "slug": "crystal-cove-el-moro-ca",
  "state": "CA",
  "region": "California",
  "lat": "33.5692",
  "lng": "-117.8399",
  "difficulty": "Easy",
  "length_mi": "4.4",
  "gain_ft": "400",
  "best_months": "Year-round",
  "trail_type": "Out & back",
  "park_name": "Crystal Cove SP",
  "alerts_url": "https://www.parks.ca.gov/?page_id=644",
  "status": "Open",
  "notes": "Coastal trail with beach access; busy weekends \u2014 reserve parking",
  "dog_friendly": "No",
  "vehicle_req": "Any",
  "score": 76,
  "score_label": "Good conditions",
  "gear_flags": [
    "mask for sensitive groups",
    "N95 mask recommended for wildfire smoke"
  ],
  "current": {
    "temp_f": 63,
    "feels_like_f": 58,
    "wind_mph": 11,
    "gusts_mph": 13,
    "rain_pct": 0
  },
  "aqi": {
    "aqi": 69,
    "category": "Moderate",
    "pollutant": "PM2.5",
    "source": "open-meteo"
  },
  "fire": {
    "risk_level": "elevated",
    "nearest_fire_km": 22.2,
    "fire_count_50km": 1
  },
  "river": null,
  "forecast": [
    {
      "date": "2026-04-27",
      "high_f": 66,
      "low_f": 55,
      "rain_pct": 9,
      "uv": 8,
      "sunrise": "2026-04-27T06:06",
      "sunset": "2026-04-27T19:31",
      "predicted_score": 76,
      "score_label": "Good conditions"
    },
    {
      "date": "2026-04-28",
      "high_f": 65,
      "low_f": 52,
      "rain_pct": 1,
      "uv": 8,
      "sunrise": "2026-04-28T06:05",
      "sunset": "2026-04-28T19:32",
      "predicted_score": 76,
      "score_label": "Good conditions"
    },
    {
      "date": "2026-04-29",
      "high_f": 71,
      "low_f": 53,
      "rain_pct": 4,
      "uv": 8,
      "sunrise": "2026-04-29T06:04",
      "sunset": "2026-04-29T19:32",
      "predicted_score": 76,
      "score_label": "Good conditions"
    },
    {
      "date": "2026-04-30",
      "high_f": 70,
      "low_f": 60,
      "rain_pct": 7,
      "uv": 8,
      "sunrise": "2026-04-30T06:03",
      "sunset": "2026-04-30T19:33",
      "predicted_score": 76,
      "score_label": "Good conditions"
    },
    {
      "date": "2026-05-01",
      "high_f": 73,
      "low_f": 62,
      "rain_pct": 3,
      "uv": 8,
      "sunrise": "2026-05-01T06:02",
      "sunset": "2026-05-01T19:34",
      "predicted_score": 76,
      "score_label": "Good conditions"
    }
  ],
  "updated_at": "2026-04-27T23:50:11.587131+00:00"
}