{
  "trail_id": "31",
  "name": "Hanging Lake",
  "slug": "hanging-lake-co",
  "state": "CO",
  "region": "Colorado",
  "lat": "39.6014",
  "lng": "-107.1866",
  "difficulty": "Hard",
  "length_mi": "2.8",
  "gain_ft": "1020",
  "best_months": "May\u2013Oct",
  "trail_type": "Out & back",
  "park_name": "White River NF",
  "alerts_url": "https://www.fs.usda.gov/whiteriver",
  "status": "Open",
  "notes": "Timed entry permit required May\u2013Oct \u2014 book Recreation.gov",
  "score": 30,
  "score_label": "Conditions poor",
  "gear_flags": [],
  "current": {},
  "aqi": {
    "aqi": null,
    "category": "Unknown",
    "pollutant": ""
  },
  "fire": {
    "risk_level": "low",
    "nearest_fire_km": 208.4,
    "fire_count_50km": 0
  },
  "river": null,
  "forecast": [],
  "updated_at": "2026-04-03T17:05:50.684356+00:00"
}