{
  "trail_id": "8",
  "name": "Wheeler Peak (NPS)",
  "slug": "wheeler-peak-great-basin-nv",
  "state": "NV",
  "region": "Nevada",
  "lat": "38.9858",
  "lng": "-114.3139",
  "difficulty": "Hard",
  "length_mi": "8.6",
  "gain_ft": "2900",
  "best_months": "Jul\u2013Sep",
  "trail_type": "Out & back",
  "park_name": "Great Basin NP",
  "alerts_url": "https://www.nps.gov/grba/planyourvisit/conditions.htm",
  "status": "Seasonal",
  "notes": "Road open late Jun \u2014 check NPS seasonal closure",
  "score": 30,
  "score_label": "Conditions poor",
  "gear_flags": [
    "insulation layer required"
  ],
  "current": {
    "temp_f": 15,
    "feels_like_f": 3,
    "wind_mph": 14,
    "gusts_mph": 20,
    "rain_pct": 20
  },
  "aqi": {
    "aqi": null,
    "category": "Unknown",
    "pollutant": ""
  },
  "river": null,
  "forecast": [
    {
      "date": "2026-04-01",
      "high_f": 21,
      "low_f": 13,
      "rain_pct": 81,
      "uv": 8
    },
    {
      "date": "2026-04-02",
      "high_f": 17,
      "low_f": 0,
      "rain_pct": 12,
      "uv": 7
    },
    {
      "date": "2026-04-03",
      "high_f": 23,
      "low_f": -3,
      "rain_pct": 2,
      "uv": 7
    },
    {
      "date": "2026-04-04",
      "high_f": 30,
      "low_f": 12,
      "rain_pct": 1,
      "uv": 8
    },
    {
      "date": "2026-04-05",
      "high_f": 37,
      "low_f": 16,
      "rain_pct": 1,
      "uv": 7
    }
  ],
  "updated_at": "2026-04-01T14:49:06.927689+00:00"
}